cybermod/__init__.py
cybermod/config.py
cybermod/config/__init__.py
cybermod/exceptions/__init__.py
cybermod/exceptions/listener_stopped.py
cybermod/exceptions/listener_timeout.py
cybermod/helpers/__init__.py
cybermod/helpers/helpers.py
cybermod/listen/__init__.py
cybermod/listen/callback_query_handler.py
cybermod/listen/chat.py
cybermod/listen/client.py
cybermod/listen/message.py
cybermod/listen/message_handler.py
cybermod/listen/user.py
cybermod/nav/__init__.py
cybermod/nav/pagination.py
cybermod/types/__init__.py
cybermod/types/identifier.py
cybermod/types/listener.py
cybermod/types/listener_types.py
cybermod/utils/__init__.py
cybermod/utils/patch.py
cybermod-5.5.1.dist-info/COPYING
cybermod-5.5.1.dist-info/COPYING.lesser
cybermod-5.5.1.dist-info/METADATA
cybermod-5.5.1.dist-info/NOTICE
cybermod-5.5.1.dist-info/WHEEL
cybermod-5.5.1.dist-info/top_level.txt
cybermod-5.5.1.dist-info/RECORD
