Metadata-Version: 2.1
Name: cybermod
Version: 5.5.1
Summary: A monkeypatcher add-on for cybergram that does conversation handling
Author: rizaldevs
Author-email: rizaldevs <rizaldaitona@gmail.com>
Requires-Python: >=3.8
License-File: COPYING
License-File: COPYING.lesser
License-File: NOTICE
Requires-Dist: cybergram (>=1.0)
